booknlp/__init__.py
booknlp/booknlp.py
booknlp/common/__init__.py
booknlp/common/b3.py
booknlp/common/calc_coref_metrics.py
booknlp/common/crf.py
booknlp/common/layered_reader.py
booknlp/common/pipelines.py
booknlp/common/sequence_eval.py
booknlp/common/sequence_layered_reader.py
booknlp/english/__init__.py
booknlp/english/bert_coref_quote_pronouns.py
booknlp/english/bert_qa.py
booknlp/english/english_booknlp.py
booknlp/english/entity_tagger.py
booknlp/english/gender_inference_model_1.py
booknlp/english/litbank_coref.py
booknlp/english/litbank_quote.py
booknlp/english/name_coref.py
booknlp/english/speaker_attribution.py
booknlp/english/tagger.py
booknlp/english/data/__init__.py
booknlp/english/data/aliases.txt
booknlp/english/data/entity_cat.tagset
booknlp/english/data/gutenberg_prop_gender_terms.txt
booknlp/english/data/supersense.tagset
booknlp/english/data/wordnet.first.sense
booknlp_wdoc-1.0.1.dist-info/LICENSE
booknlp_wdoc-1.0.1.dist-info/METADATA
booknlp_wdoc-1.0.1.dist-info/WHEEL
booknlp_wdoc-1.0.1.dist-info/top_level.txt
booknlp_wdoc-1.0.1.dist-info/RECORD
