Metadata-Version: 2.1
Name: booknlp-wdoc
Version: 1.0.1
Home-page: https://github.com/sonnygeorge/booknlp
Author: David Bamman
Author-email: dbamman@berkeley.edu
License: MIT
License-File: LICENSE
Requires-Dist: torch (>=1.7.1)
Requires-Dist: tensorflow (>=1.15)
Requires-Dist: spacy (>=3.2)
Requires-Dist: transformers (>=4.11.3)
